LICENSE
MANIFEST.in
README.md
setup.cfg
setup.py
concierge_theme_gc/__init__.py
concierge_theme_gc/admin.py
concierge_theme_gc/apps.py
concierge_theme_gc/backends.py
concierge_theme_gc/forms.py
concierge_theme_gc/models.py
concierge_theme_gc/settings.py
concierge_theme_gc/tests.py
concierge_theme_gc/urls.py
concierge_theme_gc/views.py
concierge_theme_gc/webpack-stats.json
concierge_theme_gc.egg-info/PKG-INFO
concierge_theme_gc.egg-info/SOURCES.txt
concierge_theme_gc.egg-info/dependency_links.txt
concierge_theme_gc.egg-info/top_level.txt
concierge_theme_gc/migrations/0001_initial.py
concierge_theme_gc/migrations/__init__.py
concierge_theme_gc/static/bundles/vendor.js
concierge_theme_gc/static/bundles/web.css
concierge_theme_gc/static/bundles/web.css.map
concierge_theme_gc/static/bundles/web.js
concierge_theme_gc/static/icons/account-alert.svg
concierge_theme_gc/static/icons/app-tray.svg
concierge_theme_gc/static/icons/arrow-right.svg
concierge_theme_gc/static/icons/check.svg
concierge_theme_gc/static/icons/chevron-left.svg
concierge_theme_gc/static/icons/chevron-right.svg
concierge_theme_gc/static/icons/chevron-up.svg
concierge_theme_gc/static/icons/close.svg
concierge_theme_gc/static/icons/email.svg
concierge_theme_gc/static/icons/external.svg
concierge_theme_gc/static/icons/eye.svg
concierge_theme_gc/static/icons/hamburger.svg
concierge_theme_gc/static/icons/help-outline.svg
concierge_theme_gc/static/icons/lock-open.svg
concierge_theme_gc/static/icons/lock-plus.svg
concierge_theme_gc/static/icons/os-android.svg
concierge_theme_gc/static/icons/os-apple.svg
concierge_theme_gc/static/icons/person.svg
concierge_theme_gc/static/icons/play.svg
concierge_theme_gc/static/icons/search.svg
concierge_theme_gc/static/icons/security.svg
concierge_theme_gc/static/icons/tools.svg
concierge_theme_gc/static/images/2fa.svg
concierge_theme_gc/static/images/collab_icon.png
concierge_theme_gc/static/images/favicon.png
concierge_theme_gc/static/images/hergebruik.svg
concierge_theme_gc/static/images/lamp.svg
concierge_theme_gc/static/images/logo-grey.svg
concierge_theme_gc/static/images/logo-icon.svg
concierge_theme_gc/static/images/logo.svg
